pyhelayers/__init__.py
pyhelayers/_pyhelayers_cppwrappers.cpython-310-x86_64-linux-gnu.so
pyhelayers/transformer_logistic_regression.py
pyhelayers/ext/__init__.py
pyhelayers/ext/pyfhe.py
pyhelayers/ext/pyfhecommon.py
pyhelayers/ext/replace.py
pyhelayers/ext/utils.py
pyhelayers/ext/pyfhemlimpl/__init__.py
pyhelayers/ext/pyfhemlimpl/pyfheml.py
pyhelayers/libs/_dummy.cpython-310-x86_64-linux-gnu.so
pyhelayers/mltoolbox/__init__.py
pyhelayers/mltoolbox/arguments.py
pyhelayers/mltoolbox/poly_activation_converter.py
pyhelayers/mltoolbox/trainer.py
pyhelayers/mltoolbox/data_loader/__init__.py
pyhelayers/mltoolbox/data_loader/cifar100_dataset.py
pyhelayers/mltoolbox/data_loader/cifar10_dataset.py
pyhelayers/mltoolbox/data_loader/covidCT_dataset.py
pyhelayers/mltoolbox/data_loader/covidXray_dataset.py
pyhelayers/mltoolbox/data_loader/dataset_wrapper.py
pyhelayers/mltoolbox/data_loader/ds_factory.py
pyhelayers/mltoolbox/data_loader/imagenet_dataset.py
pyhelayers/mltoolbox/data_loader/places205_dataset.py
pyhelayers/mltoolbox/data_loader/places365_dataset.py
pyhelayers/mltoolbox/he_dl_lib/__init__.py
pyhelayers/mltoolbox/he_dl_lib/distillation.py
pyhelayers/mltoolbox/he_dl_lib/my_logger.py
pyhelayers/mltoolbox/he_dl_lib/poly_activations.py
pyhelayers/mltoolbox/he_dl_lib/range_awareness.py
pyhelayers/mltoolbox/model/DNN_factory.py
pyhelayers/mltoolbox/model/__init__.py
pyhelayers/mltoolbox/model/alexnet_fhe.py
pyhelayers/mltoolbox/model/lenet5.py
pyhelayers/mltoolbox/model/nn_module.py
pyhelayers/mltoolbox/model/resnet50.py
pyhelayers/mltoolbox/model/resnet_clip.py
pyhelayers/mltoolbox/model/squeezenet.py
pyhelayers/mltoolbox/model/squeezenetchet.py
pyhelayers/mltoolbox/utils/__init__.py
pyhelayers/mltoolbox/utils/cf_matrix.py
pyhelayers/mltoolbox/utils/metrics_tracker.py
pyhelayers/mltoolbox/utils/util.py
pyhelayers/resources/default_helayers_config.json
pyhelayers/resources/er/README.md
pyhelayers/resources/er/nick_to_name.csv
pyhelayers-1.5.5.3.dist-info/LICENSE
pyhelayers-1.5.5.3.dist-info/METADATA
pyhelayers-1.5.5.3.dist-info/WHEEL
pyhelayers-1.5.5.3.dist-info/top_level.txt
pyhelayers-1.5.5.3.dist-info/RECORD
